mlflow_xgboost_proba/__init__.py
mlflow_xgboost_proba-0.3.1.dist-info/LICENSE
mlflow_xgboost_proba-0.3.1.dist-info/METADATA
mlflow_xgboost_proba-0.3.1.dist-info/WHEEL
mlflow_xgboost_proba-0.3.1.dist-info/RECORD
