Metadata-Version: 2.1
Name: mlflow-xgboost-proba
Version: 0.3.1
Summary: MLflow XGBoost flavour with probabilities
Home-page: https://github.com/sergray/mlflow-xgboost-proba
License: Apache-2.0
Author: Sergey Panfilov
Author-email: sergray@gmail.com
Requires-Python: >=3.11,<4.0
Classifier: License :: OSI Approved :: Apache Software License
Classifier: Programming Language :: Python :: 3
Classifier: Programming Language :: Python :: 3.11
Classifier: Programming Language :: Python :: 3.12
Requires-Dist: mlflow (>=2.13.1,<3.0.0)
Requires-Dist: xgboost (>=2.0.3,<3.0.0)
Project-URL: Repository, https://github.com/sergray/mlflow-xgboost-proba
